drewtils/__init__.py
drewtils/parsers.py
drewtils-0.1.9.dist-info/DESCRIPTION.rst
drewtils-0.1.9.dist-info/METADATA
drewtils-0.1.9.dist-info/RECORD
drewtils-0.1.9.dist-info/WHEEL
drewtils-0.1.9.dist-info/metadata.json
drewtils-0.1.9.dist-info/top_level.txt
