Metadata-Version: 2.0
Name: drewtils
Version: 0.1.9
Summary: Simple tools to make testing and file parsing easier
Home-page: https://github.com/drewejohnson/drewtils
Author: Andrew Johnson
Author-email: drewej@protonmail.com
License: MIT
Keywords: parsing files
Platform: UNKNOWN
Classifier: License :: OSI Approved :: MIT License
Requires-Python: >=2.7,!=3.1,!=3.2,!=3.3,!=3.4
